open_echo/cli.py
open_echo/depth_output.py
open_echo/desktop.py
open_echo/echo.py
open_echo/py.typed
open_echo/settings.py
open_echo/web.py
open_echo/assets/static/js-colormaps.js
open_echo/assets/static/style.css
open_echo/assets/templates/config.html
open_echo/assets/templates/frontend.html
open_echo/assets/templates/spectrogram.js
open_echo-0.1.1.dist-info/METADATA
open_echo-0.1.1.dist-info/WHEEL
open_echo-0.1.1.dist-info/entry_points.txt
open_echo-0.1.1.dist-info/RECORD
