Metadata-Version: 2.4
Name: open_echo
Version: 0.1.1
Summary: Python library for OpenEcho boards
Requires-Python: >=3.11
Requires-Dist: fastapi>=0.116.1
Requires-Dist: httpx>=0.28.1
Requires-Dist: jinja2>=3.1.6
Requires-Dist: numpy>=2.3.2
Requires-Dist: pydantic-settings>=2.10.1
Requires-Dist: pyqt5>=5.15.11
Requires-Dist: pyqtdarktheme>=2.1.0
Requires-Dist: pyqtgraph>=0.14.0
Requires-Dist: pyserial-asyncio-fast>=0.16
Requires-Dist: pyserial-asyncio>=0.6
Requires-Dist: pyserial<3.5
Requires-Dist: python-multipart>=0.0.20
Requires-Dist: qasync>=0.24.0
Requires-Dist: uvicorn>=0.35.0
Requires-Dist: websockets>=15.0.1
